{
  "project_info": {
    "project_number": "900010288181",
    "project_id": "android-java-practice",
    "storage_bucket": "android-java-practice.appspot.com"
  },
  "client": [
    {
      "client_info": {
        "mobilesdk_app_id": "1:900010288181:android:d5728297db12ad6b3abd7c",
        "android_client_info": {
          "package_name": "com.example.firebaseemailpass"
        }
      },
      "oauth_client": [
        {
          "client_id": "900010288181-avdt9gp1ssqpmkhlr6kdr5t5p9dp6l2h.apps.googleusercontent.com",
          "client_type": 1,
          "android_info": {
            "package_name": "com.example.firebaseemailpass",
            "certificate_hash": "ef9c4f39d1a8aba069247018c82076bb5ddd5910"
          }
        },
        {
          "client_id": "900010288181-g5o6559vpaeo1ktbkbrenps19k8dnd7s.apps.googleusercontent.com",
          "client_type": 3
        }
      ],
      "api_key": [
        {
          "current_key": "AIzaSyDXiHz18Hz5jdsfE1t0H1O3nNEgjM0K5tQ"
        }
      ],
      "services": {
        "appinvite_service": {
          "other_platform_oauth_client": [
            {
              "client_id": "900010288181-g5o6559vpaeo1ktbkbrenps19k8dnd7s.apps.googleusercontent.com",
              "client_type": 3
            }
          ]
        }
      }
    },
    {
      "client_info": {
        "mobilesdk_app_id": "1:900010288181:android:27f323bfb2396a9e3abd7c",
        "android_client_info": {
          "package_name": "com.example.firebasegoogle"
        }
      },
      "oauth_client": [
        {
          "client_id": "900010288181-3nf8t8fv17uarcpkj8j7mabaobnbsunb.apps.googleusercontent.com",
          "client_type": 1,
          "android_info": {
            "package_name": "com.example.firebasegoogle",
            "certificate_hash": "ef9c4f39d1a8aba069247018c82076bb5ddd5910"
          }
        },
        {
          "client_id": "900010288181-g5o6559vpaeo1ktbkbrenps19k8dnd7s.apps.googleusercontent.com",
          "client_type": 3
        }
      ],
      "api_key": [
        {
          "current_key": "AIzaSyDXiHz18Hz5jdsfE1t0H1O3nNEgjM0K5tQ"
        }
      ],
      "services": {
        "appinvite_service": {
          "other_platform_oauth_client": [
            {
              "client_id": "900010288181-g5o6559vpaeo1ktbkbrenps19k8dnd7s.apps.googleusercontent.com",
              "client_type": 3
            }
          ]
        }
      }
    },
    {
      "client_info": {
        "mobilesdk_app_id": "1:900010288181:android:0631822ff9b2c1093abd7c",
        "android_client_info": {
          "package_name": "com.example.sqlitetask"
        }
      },
      "oauth_client": [
        {
          "client_id": "900010288181-g5o6559vpaeo1ktbkbrenps19k8dnd7s.apps.googleusercontent.com",
          "client_type": 3
        }
      ],
      "api_key": [
        {
          "current_key": "AIzaSyDXiHz18Hz5jdsfE1t0H1O3nNEgjM0K5tQ"
        }
      ],
      "services": {
        "appinvite_service": {
          "other_platform_oauth_client": [
            {
              "client_id": "900010288181-g5o6559vpaeo1ktbkbrenps19k8dnd7s.apps.googleusercontent.com",
              "client_type": 3
            }
          ]
        }
      }
    }
  ],
  "configuration_version": "1"
}